vitvqgan/__init__.py
vitvqgan/demo_recon.py
vitvqgan/train_vim.py
vitvqgan/assets/class/imagenet.txt
vitvqgan/assets/class/lsun.txt
vitvqgan/assets/font/arial.ttf
vitvqgan/assets/vocab/bpe_simple_vocab_16e6.txt
vitvqgan/configs/imagenet_gpt_vitvq_base.yaml
vitvqgan/configs/imagenet_vitvq_base.yaml
vitvqgan/configs/imagenet_vitvq_large.yaml
vitvqgan/configs/imagenet_vitvq_small.yaml
vitvqgan/dataloader/__init__.py
vitvqgan/dataloader/cc3m.py
vitvqgan/dataloader/classimage.py
vitvqgan/dataloader/coco.py
vitvqgan/dataloader/imagenet.py
vitvqgan/dataloader/inatural.py
vitvqgan/dataloader/lsun.py
vitvqgan/dataloader/srimage.py
vitvqgan/dataloader/textimage.py
vitvqgan/losses/__init__.py
vitvqgan/losses/layers.py
vitvqgan/losses/segmentation.py
vitvqgan/losses/vqperceptual.py
vitvqgan/losses/op/__init__.py
vitvqgan/losses/op/conv2d_gradfix.py
vitvqgan/losses/op/fused_act.py
vitvqgan/losses/op/fused_bias_act.cpp
vitvqgan/losses/op/fused_bias_act_kernel.cu
vitvqgan/losses/op/upfirdn2d.cpp
vitvqgan/losses/op/upfirdn2d.py
vitvqgan/losses/op/upfirdn2d_kernel.cu
vitvqgan/modules/__init__.py
vitvqgan/modules/cond/__init__.py
vitvqgan/modules/cond/clipcond.py
vitvqgan/modules/cond/dummycond.py
vitvqgan/modules/cond/vqcond.py
vitvqgan/modules/stage1/__init__.py
vitvqgan/modules/stage1/layers.py
vitvqgan/modules/stage1/quantizers.py
vitvqgan/modules/stage1/vit_vqgan.py
vitvqgan/modules/stage2/__init__.py
vitvqgan/modules/stage2/layers.py
vitvqgan/modules/stage2/transformer.py
vitvqgan/utils/__init__.py
vitvqgan/utils/callback.py
vitvqgan/utils/general.py
vitvqgan/utils/scheduler.py
vitvqgan/utils/tokenizer.py
vitvqgan-0.0.1.dev1.dist-info/LICENSE
vitvqgan-0.0.1.dev1.dist-info/METADATA
vitvqgan-0.0.1.dev1.dist-info/WHEEL
vitvqgan-0.0.1.dev1.dist-info/top_level.txt
vitvqgan-0.0.1.dev1.dist-info/RECORD
