Metadata-Version: 2.1
Name: vitvqgan
Version: 0.0.1.dev1
Summary: VITVQGAN - VECTOR-QUANTIZED IMAGE MODELING WITH IMPROVED VQGAN
Home-page: https://github.com/henrywoo/vim
Author: Fuheng Wu
Keywords: vitvqgan
Classifier: Programming Language :: Python :: 3
Classifier: Programming Language :: Python :: 3.8
Classifier: Programming Language :: Python :: 3.9
Classifier: Programming Language :: Python :: 3.10
Classifier: Programming Language :: Python :: 3.11
Classifier: Programming Language :: Python :: 3.12
Classifier: Programming Language :: Python :: 3.13
License-File: LICENSE
